{
  "home":{
    "last_days_amount": {
        "today": 10500 ,
        "yesterday": 22500 ,
        "day_before_yesterday": 45050
      },
    "last_months_amount": [
        {
            "mois": "Janvier",
            "gains": 10500
        },
        {
            "mois": "Fevrier",
            "gains": 22500
        },
        {
            "mois": "Mars",
            "gains": 45050
        },
        {
            "mois": "Avril",
            "gains": 45050
        },
        {
            "mois": "Mai",
            "gains": 10500
        },
        {
            "mois": "Juin",
            "gains": 22500
        },
        {
            "mois": "Juillet",
            "gains": 45050
        },
        {
            "mois": "Août",
            "gains": 45050
        },
        {
            "mois": "Septembre",
            "gains": 10500
        },
        {
            "mois": "Octobre",
            "gains": 22500
        },
        {
            "mois": "Novembre",
            "gains": 45050
        },
        {
            "mois": "Decembre",
            "gains": 45050
        }
    ]
  }
}
